divbrowse/__init__.py
divbrowse/_version.py
divbrowse/brapi/__init__.py
divbrowse/brapi/v2/__init__.py
divbrowse/brapi/v2/allelematrix.py
divbrowse/calc_gene_distances.py
divbrowse/calc_variant_density.py
divbrowse/cli.py
divbrowse/divbrowse.config.yml.example
divbrowse/divbrowse.config.yml.skeleton
divbrowse/lib/__init__.py
divbrowse/lib/analysis.py
divbrowse/lib/annotation_data.py
divbrowse/lib/genotype_data.py
divbrowse/lib/utils.py
divbrowse/lib/variant_calls_slice.py
divbrowse/README.md
divbrowse/server.py
divbrowse/server_brapi.py
divbrowse/server_brapi_old.py
divbrowse/server_fastapi.py
divbrowse/server_orig.py
divbrowse/server_restx.py
divbrowse/setup.py
divbrowse/static/build/bundle.css
divbrowse/static/build/bundle.js
divbrowse/static/build/bundle.js.map
divbrowse/static/build/divbrowse.js
divbrowse/static/build/divbrowse.js.map
divbrowse/static/index.html
divbrowse/test.py
divbrowse/test_summary_stats.py
divbrowse/tests/data/divbrowse_test.vcf
divbrowse/tests/data/sample.vcf
divbrowse/variant_density.png
divbrowse/variant_density_2.png
divbrowse/variant_density_3.png
divbrowse/wsgi.py
divbrowse-1.1.0.dist-info/entry_points.txt
divbrowse-1.1.0.dist-info/LICENSE
divbrowse-1.1.0.dist-info/WHEEL
divbrowse-1.1.0.dist-info/METADATA
divbrowse-1.1.0.dist-info/RECORD
